mantis_logger/__init__.py
mantis_logger/config.py
mantis_logger/handlers.py
mantis_logger-0.2.0.dist-info/METADATA
mantis_logger-0.2.0.dist-info/WHEEL
mantis_logger-0.2.0.dist-info/RECORD
