Metadata-Version: 2.1
Name: mantis-logger
Version: 0.2.0
Summary: M&NTIS logger library
License: MIT
Author: AMOSSYS
Requires-Python: >=3.8,<4.0
Classifier: License :: OSI Approved :: MIT License
Classifier: Programming Language :: Python :: 3
Classifier: Programming Language :: Python :: 3.8
Classifier: Programming Language :: Python :: 3.9
Classifier: Programming Language :: Python :: 3.10
Classifier: Programming Language :: Python :: 3.11
Classifier: Programming Language :: Python :: 3.12
Classifier: Programming Language :: Python :: 3.13
Requires-Dist: loguru (>=0.7.2,<0.8.0)
Requires-Dist: loki-logger-handler (>=0.1.1,<0.2.0)
Requires-Dist: omegaconf (>=2.3.0,<3.0.0)
